MANIFEST.in
README.md
setup.py
pyco_utils/__adapt.py
pyco_utils/__init__.py
pyco_utils/_coimp.py
pyco_utils/_compat.py
pyco_utils/_format.py
pyco_utils/_json.py
pyco_utils/_subproc.py
pyco_utils/co_shutil.py
pyco_utils/colog.py
pyco_utils/colog2.py
pyco_utils/const.py
pyco_utils/decorators.py
pyco_utils/form_data.py
pyco_utils/path_tree.py
pyco_utils/pretty_csv.py
pyco_utils/regex.py
pyco_utils/reverify.py
pyco_utils/unzip.py
pyco_utils.egg-info/PKG-INFO
pyco_utils.egg-info/SOURCES.txt
pyco_utils.egg-info/dependency_links.txt
pyco_utils.egg-info/not-zip-safe
pyco_utils.egg-info/top_level.txt